ada_core/__init__.py
ada_core/base_handler.py
ada_core/binary_handlers.py
ada_core/common_handlers.py
ada_core/constants.py
ada_core/exceptions.py
ada_core/get_facade.py
ada_core/handler.py
ada_core/post_facade.py
ada_core/setLogging.py
ada_core/utils.py
ada_core/algorithms/__init__.py
ada_core/algorithms/algorithm_factory.py
ada_core/algorithms/algorithm_meta.py
ada_core/algorithms/binary_calculate_algorithms.py
ada_core/algorithms/binary_judge_algorithms.py
ada_core/algorithms/binary_num1num_judge_algorithms.py
ada_core/algorithms/binary_num1ts2ts_calculate_algorithms.py
ada_core/algorithms/binary_ts1num2ts_calculate_algorithms.py
ada_core/algorithms/naive_algorithm.py
ada_core/algorithms/unary_common_calculate_algorithms.py
ada_core/algorithms/unary_judge_algorithms.py
ada_core/algorithms/unary_ts2num_calculate_algorithms.py
ada_core/algorithms/unary_ts2ts_calculate_algorithms.py
ada_core/data_model/__init__.py
ada_core/data_model/entry.py
ada_core/data_model/io_data_model.py
ada_core/data_model/io_data_type.py
ada_core/data_model/metric.py
ada_core/data_model/metric_meta.py
ada_core/data_model/time_series.py
ada_core-0.3.20.dist-info/LICENSE
ada_core-0.3.20.dist-info/METADATA
ada_core-0.3.20.dist-info/WHEEL
ada_core-0.3.20.dist-info/top_level.txt
ada_core-0.3.20.dist-info/RECORD
