Metadata-Version: 2.1
Name: ada-core
Version: 0.3.20
Summary: ada_core is an anomaly detection library for timeseries data
Home-page: https://github.paypal.com/ROM/ada_core
Author: Cai, Qianwen
Author-email: cai.qianwen@hotmail.co.uk
License: UNKNOWN
Platform: UNKNOWN
Classifier: Programming Language :: Python :: 3
Classifier: License :: OSI Approved :: Apache Software License
Classifier: Operating System :: OS Independent
Requires-Dist: PyYAML (==3.12)
Requires-Dist: pytz (==2018.4)
Requires-Dist: scipy (==1.1.0)
Requires-Dist: numpy (==1.14.3)
Requires-Dist: pandas (==0.23.0)
Requires-Dist: statsmodels (==0.9.0)
Requires-Dist: schematics (==2.1.0)
